ethnicities/__init__.py
ethnicities/all_ethnicities.py
ethnicities/by_region.py
ethnicities/common.py
ethnicities/common_and_by_region.py
ethnicities/test.py
ethnicities-0.0.2.dist-info/METADATA
ethnicities-0.0.2.dist-info/WHEEL
ethnicities-0.0.2.dist-info/top_level.txt
ethnicities-0.0.2.dist-info/RECORD
